{
  "id": "771371853",
  "title": "We Come As Friends",
  "year": "2014",
  "runtime": 105,
  "synopsis": "Colonization as a human phenomenon through both explicit and metaphoric lenses without oversimplified accusations or political theorizing. Alarmingly, It is not a historical film since colonization and the slave trade still exist.",
  "tag": "Out of Africa",
  "slug": "we-come-as-friends",
  "critics_score": 96,
  "audience_score": 92,
  "directors": [

  ],
  "rt_link": "http://www.rottentomatoes.com/m/we_come_as_friends/",
  "region": "auckland",
  "reviews": [
    "9885d"
  ]
}